{
  "last_updated": "2026-07-10T10:26:48Z",
  "total_listings": 776,
  "scans": [
    {
      "date": "2026-07-10",
      "timestamp": "2026-07-10T10:26:48Z",
      "total_listings": 776,
      "added": 50,
      "removed": 43
    },
    {
      "date": "2026-07-09",
      "timestamp": "2026-07-09T10:28:13Z",
      "total_listings": 765,
      "added": 43,
      "removed": 29
    },
    {
      "date": "2026-07-08",
      "timestamp": "2026-07-08T09:29:25Z",
      "total_listings": 765,
      "added": 28,
      "removed": 19
    }
  ]
}