{
  "last_updated": "2026-07-06T11:41:00Z",
  "total_listings": 752,
  "scans": [
    {
      "date": "2026-07-06",
      "timestamp": "2026-07-06T11:41:00Z",
      "total_listings": 752,
      "added": 54,
      "removed": 22
    },
    {
      "date": "2026-07-05",
      "timestamp": "2026-07-05T09:45:02Z",
      "total_listings": 716,
      "added": 26,
      "removed": 22
    },
    {
      "date": "2026-07-04",
      "timestamp": "2026-07-04T09:27:12Z",
      "total_listings": 710,
      "added": 24,
      "removed": 34
    }
  ]
}